ptal_api/__init__.py
ptal_api/adapter.py
ptal_api/core/kb_sync/kb_iterator_config.py
ptal_api/core/kb_sync/object_time_interval.py
ptal_api/core/query_factory.py
ptal_api/core/type_mapper/app_settings/logging.conf
ptal_api/core/type_mapper/common/common.py
ptal_api/core/type_mapper/data_model/base_data_model.py
ptal_api/core/type_mapper/data_model/config_data_model.py
ptal_api/core/type_mapper/data_model/custom_data_model.py
ptal_api/core/type_mapper/model_parameters/name_code_mapping.yml
ptal_api/core/type_mapper/modules/custom_data_handler.py
ptal_api/core/type_mapper/modules/file_generator.py
ptal_api/core/type_mapper/modules/object_name_transformer.py
ptal_api/core/type_mapper/modules/type_mapping_generator.py
ptal_api/core/type_mapper/modules/type_mapping_loader/type_mapping_loader.py
ptal_api/core/type_mapper/modules/type_mapping_loader/type_mapping_loader_interface.py
ptal_api/core/values/date_dataclass.py
ptal_api/core/values/value_mapping.py
ptal_api/pretty_adapter/common.py
ptal_api/pretty_adapter/object_types.py
ptal_api/pretty_adapter/objects.py
ptal_api/pretty_adapter/pretty_adapter.py
ptal_api/pretty_adapter/property_values.py
ptal_api/pretty_adapter/transformer.py
ptal_api/providers/__init__.py
ptal_api/providers/gql_providers.py
ptal_api/schema/README.md
ptal_api/schema/__init__.py
ptal_api/schema/api_schema.py
ptal_api/schema/crawlers_api_schema.py
ptal_api/schema/tcontroller_api_schema.py
ptal_api/schema/translator_api_schema.py
ptal_api/schema/utils_api_schema.py
ptal_api/scripts/type_mapper.py
ptal_api/tdm_builder/__init__.py
ptal_api/tdm_builder/tdm_builder.py
ptal_api-0.12.10.2.dist-info/METADATA
ptal_api-0.12.10.2.dist-info/WHEEL
ptal_api-0.12.10.2.dist-info/entry_points.txt
ptal_api-0.12.10.2.dist-info/RECORD
