Metadata-Version: 2.1
Name: ptal-api
Version: 0.12.10.2
Summary: TALISMAN API adapter
Author: Evgeny Bechkalo
Author-email: bechkalo@ispras.ru
Requires-Python: >=3.8,<4.0
Classifier: Development Status :: 3 - Alpha
Classifier: Intended Audience :: Developers
Classifier: Operating System :: OS Independent
Classifier: Programming Language :: Python :: 3
Classifier: Programming Language :: Python :: 3.8
Classifier: Programming Language :: Python :: 3.9
Classifier: Programming Language :: Python :: 3.10
Classifier: Programming Language :: Python :: 3.11
Requires-Dist: click (>=8.1.3)
Requires-Dist: deprecation (>=2.1.0,<3.0.0)
Requires-Dist: graphql-core (>=3.2.3)
Requires-Dist: marshmallow-dataclass (>=8.5.11)
Requires-Dist: pyjwt (>=2.7.0)
Requires-Dist: python-keycloak (>=2.6.0)
Requires-Dist: ruamel.yaml (>=0.17.21)
Requires-Dist: sgqlc (>=16.3)
Requires-Dist: transliterate (>=1.10.2)
